{
  "משקאות": [
    { "name": "קפה שחור", "price": 8.5 },
    { "name": "קפה הפוך", "price": 12 },
    { "name": "קפוצ'ינו", "price": 14 },
    { "name": "אספרסו", "price": 10 },
    { "name": "תה", "price": 9 },
    { "name": "מיץ תפוזים", "price": 15 },
    { "name": "שייק בננה", "price": 18 },
    { "name": "לימונדה", "price": 12 }
  ],
  "מאפים": [
    { "name": "קרואסון", "price": 12 },
    { "name": "בורקס גבינה", "price": 10 },
    { "name": "מאפין שוקולד", "price": 14 },
    { "name": "בייגלה", "price": 8 },
    { "name": "רוגach", "price": 11 },
    { "name": "דניש", "price": 13 }
  ],
  "סלטים": [
    { "name": "סלט יווני", "price": 35 },
    { "name": "סלט קיסר", "price": 38 },
    { "name": "סלט טאבולה", "price": 32 },
    { "name": "סלט קולסלאו", "price": 28 },
    { "name": "סלט וולדורף", "price": 40 }
  ],
  "כריכים": [
    { "name": "כריך טונה", "price": 28 },
    { "name": "כריך גבינה צהובה", "price": 25 },
    { "name": "כריך אבוקדו", "price": 30 },
    { "name": "כריך ביצה", "price": 22 },
    { "name": "כריך כבד קצוץ", "price": 32 }
  ],
  "טוסטים": [
    { "name": "טוסט גבינה", "price": 22 },
    { "name": "טוסט טונה", "price": 26 },
    { "name": "טוסט ירקות", "price": 24 },
    { "name": "טוסט שוקולד", "price": 18 }
  ],
  "ארוחות בוקר": [
    { "name": "ארוחת בוקר ישראלית", "price": 55 },
    { "name": "ארוחת בוקר אנגלית", "price": 65 },
    { "name": "שקשוקה", "price": 42 },
    { "name": "חביתה", "price": 35 },
    { "name": "פנקייקים", "price": 48 }
  ]
}

